forgeoagent/__init__.py
forgeoagent/__main__.py
forgeoagent/cli.py
forgeoagent/main.py
forgeoagent/clients/__init__.py
forgeoagent/clients/__main__.py
forgeoagent/clients/gemini_engine.py
forgeoagent/clients/gemini/__init__.py
forgeoagent/clients/gemini/gemini_content_manager.py
forgeoagent/clients/gemini/gemini_executor.py
forgeoagent/clients/gemini/gemini_inquirer.py
forgeoagent/clients/gemini/gemini_logger.py
forgeoagent/config/__init__.py
forgeoagent/config/__main__.py
forgeoagent/config/config.py
forgeoagent/config/default_executor_prompts.py
forgeoagent/config/default_inquirer_prompts.py
forgeoagent/config/main_executor_prompts.py
forgeoagent/controller/__init__.py
forgeoagent/controller/__main__.py
forgeoagent/controller/executor_controller.py
forgeoagent/controller/inquirer_controller.py
forgeoagent/core/__init__.py
forgeoagent/core/class_analyzer.py
forgeoagent/core/helpers.py
forgeoagent/core/managers/__init__.py
forgeoagent/core/managers/agent_manager.py
forgeoagent/core/managers/api_key_manager.py
forgeoagent/core/managers/instrument_manager.py
forgeoagent/core/managers/pip_install_manager.py
forgeoagent/core/managers/security_manager.py
forgeoagent/mcp/system_prompts/code_analysier.py
forgeoagent/mcp/system_prompts/create_readme.py
forgeoagent/mcp/system_prompts/enhance_prompt.py
forgeoagent/mcp/system_prompts/enhance_text.py
forgeoagent/mcp/system_prompts/generate_email.py
forgeoagent/mcp/system_prompts/reasearch_topic.py
forgeoagent/mcp/system_prompts/refine_code.py
forgeoagent/mcp/system_prompts/regex.py
forgeoagent/mcp/system_prompts/social_response.py
forgeoagent/mcp/system_prompts/summarize_extract.py
forgeoagent/mcp/system_prompts/translator.py
forgeoagent/mcp/system_prompts/what_word.py
forgeoagent/mcp/tools/file_manupalation.py
forgeoagent/mcp/tools/odoo_regex.py
forgeoagent/mcp/tools/structure_manager.py
forgeoagent/web/__init__.py
forgeoagent/web/api.py
forgeoagent/web/requirements.txt
forgeoagent/web/services/__init__.py
forgeoagent-0.1.0.dist-info/licenses/LICENSE
forgeoagent-0.1.0.dist-info/METADATA
forgeoagent-0.1.0.dist-info/WHEEL
forgeoagent-0.1.0.dist-info/entry_points.txt
forgeoagent-0.1.0.dist-info/top_level.txt
forgeoagent-0.1.0.dist-info/RECORD
