Metadata-Version: 2.4
Name: forgeoagent
Version: 0.1.0
Summary: ForgeOAgent - An AI agent framework
Home-page: https://github.com/angelkoradiya/forgeoagent
Author: Angel Koradiya
Author-email: Angel Koradiya <koradiyaangel11@gmail.com>
Project-URL: Homepage, https://forgeoagent.vercel.app
Project-URL: Documentation, https://github.com/angelkoradiya/forgeoagent#readme
Project-URL: Repository, https://github.com/angelkoradiya/forgeoagent
Project-URL: Issues, https://github.com/angelkoradiya/forgeoagent/issues
Classifier: Development Status :: 3 - Alpha
Classifier: Intended Audience :: Developers
Classifier: Topic :: Software Development :: Libraries :: Python Modules
Classifier: License :: OSI Approved :: MIT License
Classifier: Programming Language :: Python :: 3.12
Requires-Python: >=3.12
License-File: LICENSE
Requires-Dist: requests>=2.32.0
Requires-Dist: python-dotenv>=1.0.0
Requires-Dist: google-genai>=1.25.0
Requires-Dist: google-api-core>=2.25.0
Requires-Dist: google-generativeai>=0.8.0
Requires-Dist: fastapi>=0.119.0
Requires-Dist: python-multipart>=0.0.20
Requires-Dist: uvicorn>=0.37.0
Requires-Dist: jinja2>=3.1.0
Requires-Dist: bs4
Provides-Extra: gui
Requires-Dist: wxPython>=4.2.3; extra == "gui"
Dynamic: author
Dynamic: home-page
Dynamic: license-file
Dynamic: requires-python
